quantfinance/__init__.py
quantfinance/portfolio/__init__.py
quantfinance/portfolio/allocation.py
quantfinance/portfolio/backtesting.py
quantfinance/portfolio/optimization.py
quantfinance/portfolio/rebalancing.py
quantfinance/pricing/__init__.py
quantfinance/pricing/bonds.py
quantfinance/pricing/options.py
quantfinance/risk/__init__.py
quantfinance/risk/metrics.py
quantfinance/risk/var.py
quantfinance/utils/__init__.py
quantfinance/utils/data.py
quantfinance/utils/helpers.py
quantfinance/utils/plotting.py
quantfinance-0.1.3.dist-info/licenses/LICENSE
quantfinance-0.1.3.dist-info/METADATA
quantfinance-0.1.3.dist-info/WHEEL
quantfinance-0.1.3.dist-info/entry_points.txt
quantfinance-0.1.3.dist-info/top_level.txt
quantfinance-0.1.3.dist-info/RECORD
