Metadata-Version: 2.4
Name: quantfinance
Version: 0.1.3
Summary: Package Python complet pour la finance quantitative
Home-page: https://github.com/Mafoya1er/quantfinance
Author: Marcel ALOEKPO
Author-email: Marcel ALOEKPO <marcelaloekpo@gmail.com>
Maintainer-email: Marcel ALOEKPO <marcelaloekpo@gmail.com>
License-Expression: MIT
Project-URL: Homepage, https://github.com/votre-username/quantfinance
Project-URL: Documentation, https://quantfinance.readthedocs.io
Project-URL: Repository, https://github.com/votre-username/quantfinance
Project-URL: Bug Tracker, https://github.com/votre-username/quantfinance/issues
Project-URL: Changelog, https://github.com/votre-username/quantfinance/blob/main/CHANGELOG.md
Keywords: finance,quantitative finance,portfolio optimization,risk management,options pricing,derivatives,black-scholes,var,backtesting
Classifier: Development Status :: 3 - Alpha
Classifier: Intended Audience :: Financial and Insurance Industry
Classifier: Intended Audience :: Science/Research
Classifier: Topic :: Office/Business :: Financial :: Investment
Classifier: Programming Language :: Python :: 3
Classifier: Programming Language :: Python :: 3.8
Classifier: Programming Language :: Python :: 3.9
Classifier: Programming Language :: Python :: 3.10
Classifier: Programming Language :: Python :: 3.11
Classifier: Operating System :: OS Independent
Classifier: Typing :: Typed
Requires-Python: >=3.8
License-File: LICENSE
Requires-Dist: numpy>=1.21.0
Requires-Dist: pandas>=1.3.0
Requires-Dist: scipy>=1.7.0
Requires-Dist: matplotlib>=3.4.0
Requires-Dist: seaborn>=0.11.0
Provides-Extra: dev
Requires-Dist: pytest>=7.0.0; extra == "dev"
Requires-Dist: pytest-cov>=3.0.0; extra == "dev"
Requires-Dist: pytest-xdist>=2.5.0; extra == "dev"
Requires-Dist: black>=22.0.0; extra == "dev"
Requires-Dist: flake8>=4.0.0; extra == "dev"
Requires-Dist: mypy>=0.950; extra == "dev"
Requires-Dist: pylint>=2.13.0; extra == "dev"
Requires-Dist: isort>=5.10.0; extra == "dev"
Requires-Dist: pre-commit>=2.17.0; extra == "dev"
Provides-Extra: docs
Requires-Dist: sphinx>=4.5.0; extra == "docs"
Requires-Dist: sphinx-rtd-theme>=1.0.0; extra == "docs"
Requires-Dist: sphinx-autodoc-typehints>=1.18.0; extra == "docs"
Requires-Dist: myst-parser>=0.17.0; extra == "docs"
Provides-Extra: data
Requires-Dist: yfinance>=0.2.0; extra == "data"
Requires-Dist: pandas-datareader>=0.10.0; extra == "data"
Provides-Extra: viz
Requires-Dist: plotly>=5.0.0; extra == "viz"
Requires-Dist: mplfinance>=0.12.0; extra == "viz"
Provides-Extra: ml
Requires-Dist: scikit-learn>=1.0.0; extra == "ml"
Requires-Dist: tensorflow>=2.8.0; extra == "ml"
Provides-Extra: all
Requires-Dist: quantfinance[data,dev,docs,ml,viz]; extra == "all"
Dynamic: author
Dynamic: home-page
Dynamic: license-file
Dynamic: requires-python
